latticeflow/go/__init__.py
latticeflow/go/base.py
latticeflow/go/client.py
latticeflow/go/py.typed
latticeflow/go/version.py
latticeflow/go/_generated/__init__.py
latticeflow/go/_generated/client.py
latticeflow/go/_generated/errors.py
latticeflow/go/_generated/py.typed
latticeflow/go/_generated/types.py
latticeflow/go/_generated/api/__init__.py
latticeflow/go/_generated/api/ai_apps/__init__.py
latticeflow/go/_generated/api/ai_apps/create_ai_app.py
latticeflow/go/_generated/api/ai_apps/delete_ai_app.py
latticeflow/go/_generated/api/ai_apps/delete_ai_app_artifact.py
latticeflow/go/_generated/api/ai_apps/get_ai_app.py
latticeflow/go/_generated/api/ai_apps/get_ai_app_artifact.py
latticeflow/go/_generated/api/ai_apps/get_ai_apps.py
latticeflow/go/_generated/api/ai_apps/update_ai_app.py
latticeflow/go/_generated/api/ai_apps/update_ai_app_tags.py
latticeflow/go/_generated/api/ai_apps/upload_ai_app_artifact.py
latticeflow/go/_generated/api/dataset_generators/__init__.py
latticeflow/go/_generated/api/dataset_generators/create_dataset_generator.py
latticeflow/go/_generated/api/dataset_generators/delete_dataset_generator.py
latticeflow/go/_generated/api/dataset_generators/generate_dataset.py
latticeflow/go/_generated/api/dataset_generators/get_dataset_generator.py
latticeflow/go/_generated/api/dataset_generators/get_dataset_generators.py
latticeflow/go/_generated/api/dataset_generators/preview_dataset_generation.py
latticeflow/go/_generated/api/dataset_generators/update_dataset_generator.py
latticeflow/go/_generated/api/datasets/__init__.py
latticeflow/go/_generated/api/datasets/create_dataset.py
latticeflow/go/_generated/api/datasets/delete_dataset.py
latticeflow/go/_generated/api/datasets/get_dataset.py
latticeflow/go/_generated/api/datasets/get_dataset_head.py
latticeflow/go/_generated/api/datasets/get_datasets.py
latticeflow/go/_generated/api/datasets/update_dataset.py
latticeflow/go/_generated/api/datasets/update_dataset_data.py
latticeflow_go_sdk-2.0.0.dist-info/METADATA
latticeflow_go_sdk-2.0.0.dist-info/WHEEL
latticeflow_go_sdk-2.0.0.dist-info/entry_points.txt
latticeflow_go_sdk-2.0.0.dist-info/RECORD
