Metadata-Version: 2.4
Name: latticeflow-go-sdk
Version: 2.0.0
Summary: Latticeflow AI GO! SDK.
Project-URL: Homepage, https://latticeflow.ai/
License-Expression: LicenseRef-Proprietary
Requires-Python: >=3.9
Requires-Dist: attrs>=22.2.0
Requires-Dist: click==8.1.7
Requires-Dist: httpx<0.29.0,>=0.20.0
Requires-Dist: pydantic==2.11.7
Requires-Dist: pyperclip
Requires-Dist: python-dateutil~=2.9.0
Requires-Dist: python-dotenv>=1.1.0
Requires-Dist: pyyaml>=5.0.0
Requires-Dist: questionary==2.1.1
Requires-Dist: requests==2.32.5
Requires-Dist: tomli; python_version < '3.11'
Requires-Dist: typer==0.19.2
Provides-Extra: eval
Requires-Dist: types-tqdm==4.67.0.20250417; extra == 'eval'
Provides-Extra: test
Requires-Dist: jinja2~=3.1.5; extra == 'test'
Requires-Dist: mypy==1.18.1; extra == 'test'
Requires-Dist: polyfactory; extra == 'test'
Requires-Dist: pytest-asyncio; extra == 'test'
Requires-Dist: pytest-extra-durations~=0.1.3; extra == 'test'
Requires-Dist: pytest-mock~=3.8.2; extra == 'test'
Requires-Dist: pytest~=8.3.5; extra == 'test'
Requires-Dist: ruff==0.11.6; extra == 'test'
Requires-Dist: types-jinja2; extra == 'test'
Requires-Dist: types-pyyaml==6.0.12.20250402; extra == 'test'
Requires-Dist: types-requests; extra == 'test'
